pydiful/__init__.py
pydiful/pydiful.py
pydiful/utils.py
pydiful/exceptions/__init__.py
pydiful/exceptions/exceptions.py
pydiful/interfaces/HostApplicationBuilder.py
pydiful/interfaces/ServiceCollection.py
pydiful/interfaces/ServiceProvider.py
pydiful/interfaces/__init__.py
pydiful/mocks/__init__.py
pydiful/mocks/mocks.py
pydiful-0.1.1.dist-info/METADATA
pydiful-0.1.1.dist-info/WHEEL
pydiful-0.1.1.dist-info/licenses/LICENSE
pydiful-0.1.1.dist-info/RECORD
