Metadata-Version: 2.4
Name: pydiful
Version: 0.1.1
Summary: Dependency-Injection Framework inspired by ASP.NET.
Project-URL: Homepage, https://github.com/eHorn96/pydiful
Project-URL: Issues, https://github.com/eHorn/pydiful/issues
Author-email: Erik Horn <info@erikhorn.de>
License-Expression: GPL-3.0-only
License-File: LICENSE
Classifier: Intended Audience :: Developers
Classifier: Operating System :: OS Independent
Classifier: Programming Language :: Python :: 3.12
Requires-Python: >=3.12
Requires-Dist: coverage>=7.6.12
Requires-Dist: dataclasses>=0.8
Requires-Dist: hatchling>=1.27.0
Requires-Dist: loguru>=0.7.3
Requires-Dist: pydantic>=2.10.6
Requires-Dist: setuptools>=76.0.0
Requires-Dist: wheel>=0.45.1
